{
  "major_god": [
    "Fuxi",
    "Nuwa",
    "Shennong"
  ],
  "name": "Fast Chinese 2 TC",
  "author": "Morley Games",
  "source": "https://youtu.be/bOn4ASvDmvU",
  "build_order": [
    {
      "worker_count": 10,
      "age": 1,
      "resources": {
        "food": 7,
        "wood": 0,
        "gold": 1,
        "favor": 0
      },
      "notes": [
        "First 2 @chinese_civilian/peasant.webp@ to @resource/food.webp@ (build @chinese_building/silo.webp@) | 5 next @chinese_civilian/peasant.webp@ to @resource/food.webp@",
        "@chinese_civilian/kuafu.webp@ builds @other/house.webp@, then to @resource/gold.webp@ (build @chinese_building/silo.webp@)"
      ],
      "time": "1:15"
    },
    {
      "worker_count": 13,
      "age": 1,
      "resources": {
        "food": 7,
        "wood": 4,
        "gold": 0,
        "favor": 0
      },
      "notes": [
        "At 250 @resource/gold.webp@, move @chinese_civilian/kuafu.webp@ to @resource/wood.webp@ (build @chinese_building/silo.webp@)",
        "Next 3 @chinese_civilian/peasant.webp@ to @resource/wood.webp@"
      ],
      "time": "2:00"
    },
    {
      "worker_count": 17,
      "age": 1,
      "resources": {
        "food": 7,
        "wood": 3,
        "gold": 3,
        "favor": 0
      },
      "notes": [
        "Build @temple/temple.webp@ with @resource/wood.webp@@chinese_civilian/kuafu.webp@, then to @resource/gold.webp@",
        "Train 1 @chinese_civilian/kuafu.webp@ & 1 @chinese_civilian/peasant.webp@, both to @resource/gold.webp@ | 2:45 @age/classical_age.webp@ (drop @resource/food.webp@)"
      ],
      "time": "2:45"
    },
    {
      "worker_count": 17,
      "age": 2,
      "resources": {
        "food": 2,
        "wood": 8,
        "gold": 2,
        "favor": 0
      },
      "notes": [
        "Before @age/classical_age.webp@ | Move 5 @resource/food.webp@@chinese_civilian/peasant.webp@ to @resource/wood.webp@",
        "Send 1 @chinese_civilian/kuafu.webp@ to future @town_center/town_center.webp@ at 75% up"
      ],
      "time": "3:45"
    },
    {
      "worker_count": 19,
      "age": 2,
      "resources": {
        "food": 7,
        "wood": 3,
        "gold": 4,
        "favor": 0
      },
      "notes": [
        "In @age/classical_age.webp@ | Send the 5 @resource/wood.webp@@chinese_civilian/peasant.webp@ back to @resource/food.webp@",
        "Build @town_center/town_center.webp@ with @chinese_civilian/kuafu.webp@, then to @resource/wood.webp@ | Next 2 @chinese_civilian/peasant.webp@ to @resource/gold.webp@"
      ],
      "time": "4:25"
    },
    {
      "worker_count": 26,
      "age": 2,
      "resources": {
        "food": 9,
        "wood": 6,
        "gold": 5,
        "favor": 0
      },
      "notes": [
        "Build @other/house.webp@ with 1 @chinese_civilian/kuafu.webp@ | Add 1 @chinese_civilian/kuafu.webp@ to @resource/gold.webp@",
        "Next @chinese_civilian/peasant.webp@ to @resource/food.webp@ & @resource/wood.webp@"
      ],
      "time": "5:15"
    }
  ]
}